fhir_reada/__init__.py
fhir_reada/cli.py
fhir_reada/cohort_builder.py
fhir_reada/deid_utils.py
fhir_reada/exporter.py
fhir_reada/fhir_connector.py
fhir_reada-0.1.3.dist-info/LICENSE
fhir_reada-0.1.3.dist-info/METADATA
fhir_reada-0.1.3.dist-info/WHEEL
fhir_reada-0.1.3.dist-info/entry_points.txt
fhir_reada-0.1.3.dist-info/top_level.txt
fhir_reada-0.1.3.dist-info/RECORD
